{
  "AudioHash": "a8e702b024a11a96d6847a4fbce6b4c9",
  "AudioId": "rbxassetid://8576108789",
  "BackgroundId": "http://www.roblox.com/asset/?id=8576211995",
  "BaseRate": 1,
  "HitObjects": [
    {
      "EndTime": 1383,
      "Lane": 1,
      "StartTime": 1233,
      "Type": 2
    },
    {
      "EndTime": 1233,
      "Lane": 2,
      "StartTime": 1233,
      "Type": 1
    },
    {
      "EndTime": 1833,
      "Lane": 3,
      "StartTime": 1683,
      "Type": 2
    },
    {
      "EndTime": 2283,
      "Lane": 2,
      "StartTime": 2133,
      "Type": 2
    },
    {
      "EndTime": 2583,
      "Lane": 4,
      "StartTime": 2433,
      "Type": 2
    },
    {
      "EndTime": 3033,
      "Lane": 3,
      "StartTime": 2883,
      "Type": 2
    },
    {
      "EndTime": 3483,
      "Lane": 1,
      "StartTime": 3333,
      "Type": 2
    },
    {
      "EndTime": 3783,
      "Lane": 4,
      "StartTime": 3633,
      "Type": 2
    },
    {
      "EndTime": 4233,
      "Lane": 3,
      "StartTime": 4083,
      "Type": 2
    },
    {
      "EndTime": 4683,
      "Lane": 2,
      "StartTime": 4533,
      "Type": 2
    },
    {
      "EndTime": 4983,
      "Lane": 1,
      "StartTime": 4833,
      "Type": 2
    },
    {
      "EndTime": 5433,
      "Lane": 4,
      "StartTime": 5283,
      "Type": 2
    },
    {
      "EndTime": 5883,
      "Lane": 2,
      "StartTime": 5733,
      "Type": 2
    },
    {
      "EndTime": 6183,
      "Lane": 3,
      "StartTime": 6033,
      "Type": 2
    },
    {
      "EndTime": 6633,
      "Lane": 1,
      "StartTime": 6483,
      "Type": 2
    },
    {
      "EndTime": 7083,
      "Lane": 3,
      "StartTime": 6933,
      "Type": 2
    },
    {
      "EndTime": 7383,
      "Lane": 2,
      "StartTime": 7233,
      "Type": 2
    },
    {
      "EndTime": 7833,
      "Lane": 1,
      "StartTime": 7683,
      "Type": 2
    },
    {
      "EndTime": 8283,
      "Lane": 4,
      "StartTime": 8133,
      "Type": 2
    },
    {
      "EndTime": 8583,
      "Lane": 2,
      "StartTime": 8433,
      "Type": 2
    },
    {
      "EndTime": 9033,
      "Lane": 3,
      "StartTime": 8883,
      "Type": 2
    },
    {
      "EndTime": 9483,
      "Lane": 4,
      "StartTime": 9333,
      "Type": 2
    },
    {
      "EndTime": 9783,
      "Lane": 1,
      "StartTime": 9633,
      "Type": 2
    },
    {
      "EndTime": 10233,
      "Lane": 3,
      "StartTime": 10083,
      "Type": 2
    },
    {
      "EndTime": 10683,
      "Lane": 2,
      "StartTime": 10533,
      "Type": 2
    },
    {
      "EndTime": 10983,
      "Lane": 4,
      "StartTime": 10833,
      "Type": 2
    },
    {
      "EndTime": 10983,
      "Lane": 3,
      "StartTime": 10833,
      "Type": 2
    },
    {
      "EndTime": 11433,
      "Lane": 1,
      "StartTime": 11283,
      "Type": 2
    },
    {
      "EndTime": 11883,
      "Lane": 3,
      "StartTime": 11733,
      "Type": 2
    },
    {
      "EndTime": 12033,
      "Lane": 1,
      "StartTime": 12033,
      "Type": 1
    },
    {
      "EndTime": 12183,
      "Lane": 2,
      "StartTime": 12033,
      "Type": 2
    },
    {
      "EndTime": 12633,
      "Lane": 4,
      "StartTime": 12483,
      "Type": 2
    },
    {
      "EndTime": 13083,
      "Lane": 1,
      "StartTime": 12933,
      "Type": 2
    },
    {
      "EndTime": 13383,
      "Lane": 3,
      "StartTime": 13233,
      "Type": 2
    },
    {
      "EndTime": 13233,
      "Lane": 4,
      "StartTime": 13233,
      "Type": 1
    },
    {
      "EndTime": 13833,
      "Lane": 2,
      "StartTime": 13683,
      "Type": 2
    },
    {
      "EndTime": 14283,
      "Lane": 4,
      "StartTime": 14133,
      "Type": 2
    },
    {
      "EndTime": 14583,
      "Lane": 1,
      "StartTime": 14433,
      "Type": 2
    },
    {
      "EndTime": 14433,
      "Lane": 2,
      "StartTime": 14433,
      "Type": 1
    },
    {
      "EndTime": 15033,
      "Lane": 3,
      "StartTime": 14883,
      "Type": 2
    },
    {
      "EndTime": 15483,
      "Lane": 2,
      "StartTime": 15333,
      "Type": 2
    },
    {
      "EndTime": 15633,
      "Lane": 4,
      "StartTime": 15633,
      "Type": 1
    },
    {
      "EndTime": 15633,
      "Lane": 1,
      "StartTime": 15633,
      "Type": 1
    },
    {
      "EndTime": 15933,
      "Lane": 3,
      "StartTime": 15933,
      "Type": 1
    },
    {
      "EndTime": 16233,
      "Lane": 2,
      "StartTime": 16233,
      "Type": 1
    },
    {
      "EndTime": 16533,
      "Lane": 1,
      "StartTime": 16533,
      "Type": 1
    },
    {
      "EndTime": 16833,
      "Lane": 3,
      "StartTime": 16833,
      "Type": 1
    },
    {
      "EndTime": 16833,
      "Lane": 4,
      "StartTime": 16833,
      "Type": 1
    },
    {
      "EndTime": 17133,
      "Lane": 2,
      "StartTime": 17133,
      "Type": 1
    },
    {
      "EndTime": 17433,
      "Lane": 1,
      "StartTime": 17433,
      "Type": 1
    },
    {
      "EndTime": 17733,
      "Lane": 3,
      "StartTime": 17733,
      "Type": 1
    },
    {
      "EndTime": 18633,
      "Lane": 1,
      "StartTime": 18033,
      "Type": 2
    },
    {
      "EndTime": 18033,
      "Lane": 4,
      "StartTime": 18033,
      "Type": 1
    },
    {
      "EndTime": 18633,
      "Lane": 2,
      "StartTime": 18333,
      "Type": 2
    },
    {
      "EndTime": 19233,
      "Lane": 3,
      "StartTime": 18633,
      "Type": 2
    },
    {
      "EndTime": 19233,
      "Lane": 2,
      "StartTime": 18933,
      "Type": 2
    },
    {
      "EndTime": 19833,
      "Lane": 1,
      "StartTime": 19233,
      "Type": 2
    },
    {
      "EndTime": 20433,
      "Lane": 3,
      "StartTime": 19833,
      "Type": 2
    },
    {
      "EndTime": 20433,
      "Lane": 1,
      "StartTime": 20433,
      "Type": 1
    },
    {
      "EndTime": 20433,
      "Lane": 4,
      "StartTime": 20433,
      "Type": 1
    },
    {
      "EndTime": 20733,
      "Lane": 2,
      "StartTime": 20733,
      "Type": 1
    },
    {
      "EndTime": 21033,
      "Lane": 3,
      "StartTime": 21033,
      "Type": 1
    },
    {
      "EndTime": 21333,
      "Lane": 4,
      "StartTime": 21333,
      "Type": 1
    },
    {
      "EndTime": 21633,
      "Lane": 1,
      "StartTime": 21633,
      "Type": 1
    },
    {
      "EndTime": 21633,
      "Lane": 3,
      "StartTime": 21633,
      "Type": 1
    },
    {
      "EndTime": 21933,
      "Lane": 2,
      "StartTime": 21933,
      "Type": 1
    },
    {
      "EndTime": 22233,
      "Lane": 1,
      "StartTime": 22233,
      "Type": 1
    },
    {
      "EndTime": 22533,
      "Lane": 4,
      "StartTime": 22533,
      "Type": 1
    },
    {
      "EndTime": 22833,
      "Lane": 1,
      "StartTime": 22833,
      "Type": 1
    },
    {
      "EndTime": 22833,
      "Lane": 2,
      "StartTime": 22833,
      "Type": 1
    },
    {
      "EndTime": 23133,
      "Lane": 3,
      "StartTime": 23133,
      "Type": 1
    },
    {
      "EndTime": 23433,
      "Lane": 4,
      "StartTime": 23433,
      "Type": 1
    },
    {
      "EndTime": 23733,
      "Lane": 1,
      "StartTime": 23733,
      "Type": 1
    },
    {
      "EndTime": 24033,
      "Lane": 3,
      "StartTime": 24033,
      "Type": 1
    },
    {
      "EndTime": 24033,
      "Lane": 4,
      "StartTime": 24033,
      "Type": 1
    },
    {
      "EndTime": 24333,
      "Lane": 2,
      "StartTime": 24333,
      "Type": 1
    },
    {
      "EndTime": 24933,
      "Lane": 1,
      "StartTime": 24633,
      "Type": 2
    },
    {
      "EndTime": 25233,
      "Lane": 4,
      "StartTime": 24933,
      "Type": 2
    },
    {
      "EndTime": 25233,
      "Lane": 2,
      "StartTime": 25233,
      "Type": 1
    },
    {
      "EndTime": 25233,
      "Lane": 1,
      "StartTime": 25233,
      "Type": 1
    },
    {
      "EndTime": 25533,
      "Lane": 3,
      "StartTime": 25533,
      "Type": 1
    },
    {
      "EndTime": 25833,
      "Lane": 4,
      "StartTime": 25833,
      "Type": 1
    },
    {
      "EndTime": 26133,
      "Lane": 1,
      "StartTime": 26133,
      "Type": 1
    },
    {
      "EndTime": 26433,
      "Lane": 3,
      "StartTime": 26433,
      "Type": 1
    },
    {
      "EndTime": 26433,
      "Lane": 4,
      "StartTime": 26433,
      "Type": 1
    },
    {
      "EndTime": 26733,
      "Lane": 2,
      "StartTime": 26733,
      "Type": 1
    },
    {
      "EndTime": 27033,
      "Lane": 1,
      "StartTime": 27033,
      "Type": 1
    },
    {
      "EndTime": 27333,
      "Lane": 4,
      "StartTime": 27333,
      "Type": 1
    },
    {
      "EndTime": 27633,
      "Lane": 1,
      "StartTime": 27633,
      "Type": 1
    },
    {
      "EndTime": 27633,
      "Lane": 2,
      "StartTime": 27633,
      "Type": 1
    },
    {
      "EndTime": 27933,
      "Lane": 3,
      "StartTime": 27933,
      "Type": 1
    },
    {
      "EndTime": 28533,
      "Lane": 4,
      "StartTime": 28233,
      "Type": 2
    },
    {
      "EndTime": 28833,
      "Lane": 1,
      "StartTime": 28533,
      "Type": 2
    },
    {
      "EndTime": 28833,
      "Lane": 3,
      "StartTime": 28833,
      "Type": 1
    },
    {
      "EndTime": 28833,
      "Lane": 4,
      "StartTime": 28833,
      "Type": 1
    },
    {
      "EndTime": 29133,
      "Lane": 1,
      "StartTime": 29133,
      "Type": 1
    },
    {
      "EndTime": 29733,
      "Lane": 2,
      "StartTime": 29283,
      "Type": 2
    },
    {
      "EndTime": 29283,
      "Lane": 4,
      "StartTime": 29283,
      "Type": 1
    },
    {
      "EndTime": 30033,
      "Lane": 1,
      "StartTime": 29733,
      "Type": 2
    },
    {
      "EndTime": 30033,
      "Lane": 4,
      "StartTime": 30033,
      "Type": 1
    },
    {
      "EndTime": 30033,
      "Lane": 3,
      "StartTime": 30033,
      "Type": 1
    },
    {
      "EndTime": 30333,
      "Lane": 1,
      "StartTime": 30333,
      "Type": 1
    },
    {
      "EndTime": 30333,
      "Lane": 2,
      "StartTime": 30333,
      "Type": 1
    },
    {
      "EndTime": 30633,
      "Lane": 3,
      "StartTime": 30633,
      "Type": 1
    },
    {
      "EndTime": 30933,
      "Lane": 4,
      "StartTime": 30933,
      "Type": 1
    },
    {
      "EndTime": 30933,
      "Lane": 1,
      "StartTime": 30933,
      "Type": 1
    },
    {
      "EndTime": 31233,
      "Lane": 3,
      "StartTime": 31233,
      "Type": 1
    },
    {
      "EndTime": 31533,
      "Lane": 1,
      "StartTime": 31533,
      "Type": 1
    },
    {
      "EndTime": 31533,
      "Lane": 2,
      "StartTime": 31533,
      "Type": 1
    },
    {
      "EndTime": 31833,
      "Lane": 3,
      "StartTime": 31833,
      "Type": 1
    },
    {
      "EndTime": 32133,
      "Lane": 1,
      "StartTime": 32133,
      "Type": 1
    },
    {
      "EndTime": 32133,
      "Lane": 4,
      "StartTime": 32133,
      "Type": 1
    },
    {
      "EndTime": 32433,
      "Lane": 2,
      "StartTime": 32433,
      "Type": 1
    },
    {
      "EndTime": 32733,
      "Lane": 1,
      "StartTime": 32733,
      "Type": 1
    },
    {
      "EndTime": 32733,
      "Lane": 3,
      "StartTime": 32733,
      "Type": 1
    },
    {
      "EndTime": 33333,
      "Lane": 4,
      "StartTime": 33033,
      "Type": 2
    },
    {
      "EndTime": 33633,
      "Lane": 1,
      "StartTime": 33333,
      "Type": 2
    },
    {
      "EndTime": 33333,
      "Lane": 2,
      "StartTime": 33333,
      "Type": 1
    },
    {
      "EndTime": 33933,
      "Lane": 3,
      "StartTime": 33633,
      "Type": 2
    },
    {
      "EndTime": 33933,
      "Lane": 4,
      "StartTime": 33933,
      "Type": 1
    },
    {
      "EndTime": 33933,
      "Lane": 1,
      "StartTime": 33933,
      "Type": 1
    },
    {
      "EndTime": 34233,
      "Lane": 1,
      "StartTime": 34233,
      "Type": 1
    },
    {
      "EndTime": 34533,
      "Lane": 2,
      "StartTime": 34233,
      "Type": 2
    },
    {
      "EndTime": 34833,
      "Lane": 3,
      "StartTime": 34533,
      "Type": 2
    },
    {
      "EndTime": 34533,
      "Lane": 4,
      "StartTime": 34533,
      "Type": 1
    },
    {
      "EndTime": 34833,
      "Lane": 1,
      "StartTime": 34833,
      "Type": 1
    },
    {
      "EndTime": 35133,
      "Lane": 4,
      "StartTime": 35133,
      "Type": 1
    },
    {
      "EndTime": 35133,
      "Lane": 3,
      "StartTime": 35133,
      "Type": 1
    },
    {
      "EndTime": 35433,
      "Lane": 2,
      "StartTime": 35433,
      "Type": 1
    },
    {
      "EndTime": 35733,
      "Lane": 1,
      "StartTime": 35733,
      "Type": 1
    },
    {
      "EndTime": 35733,
      "Lane": 3,
      "StartTime": 35733,
      "Type": 1
    },
    {
      "EndTime": 36333,
      "Lane": 2,
      "StartTime": 36033,
      "Type": 2
    },
    {
      "EndTime": 36333,
      "Lane": 3,
      "StartTime": 36333,
      "Type": 1
    },
    {
      "EndTime": 36633,
      "Lane": 4,
      "StartTime": 36333,
      "Type": 2
    },
    {
      "EndTime": 36933,
      "Lane": 1,
      "StartTime": 36633,
      "Type": 2
    },
    {
      "EndTime": 37233,
      "Lane": 2,
      "StartTime": 36933,
      "Type": 2
    },
    {
      "EndTime": 36933,
      "Lane": 4,
      "StartTime": 36933,
      "Type": 1
    },
    {
      "EndTime": 37233,
      "Lane": 1,
      "StartTime": 37233,
      "Type": 1
    },
    {
      "EndTime": 37233,
      "Lane": 4,
      "StartTime": 37233,
      "Type": 1
    },
    {
      "EndTime": 37533,
      "Lane": 2,
      "StartTime": 37533,
      "Type": 1
    },
    {
      "EndTime": 37533,
      "Lane": 3,
      "StartTime": 37533,
      "Type": 1
    },
    {
      "EndTime": 37833,
      "Lane": 1,
      "StartTime": 37833,
      "Type": 1
    },
    {
      "EndTime": 37983,
      "Lane": 2,
      "StartTime": 37983,
      "Type": 1
    },
    {
      "EndTime": 38133,
      "Lane": 3,
      "StartTime": 38133,
      "Type": 1
    },
    {
      "EndTime": 38433,
      "Lane": 4,
      "StartTime": 38133,
      "Type": 2
    },
    {
      "EndTime": 38433,
      "Lane": 1,
      "StartTime": 38433,
      "Type": 1
    },
    {
      "EndTime": 38583,
      "Lane": 2,
      "StartTime": 38583,
      "Type": 1
    },
    {
      "EndTime": 38733,
      "Lane": 4,
      "StartTime": 38733,
      "Type": 1
    },
    {
      "EndTime": 38883,
      "Lane": 3,
      "StartTime": 38883,
      "Type": 1
    },
    {
      "EndTime": 39033,
      "Lane": 2,
      "StartTime": 39033,
      "Type": 1
    },
    {
      "EndTime": 39333,
      "Lane": 1,
      "StartTime": 39033,
      "Type": 2
    },
    {
      "EndTime": 39333,
      "Lane": 3,
      "StartTime": 39333,
      "Type": 1
    },
    {
      "EndTime": 39483,
      "Lane": 2,
      "StartTime": 39483,
      "Type": 1
    },
    {
      "EndTime": 39933,
      "Lane": 1,
      "StartTime": 39633,
      "Type": 2
    },
    {
      "EndTime": 39933,
      "Lane": 4,
      "StartTime": 39633,
      "Type": 2
    },
    {
      "EndTime": 39933,
      "Lane": 2,
      "StartTime": 39933,
      "Type": 1
    },
    {
      "EndTime": 40083,
      "Lane": 3,
      "StartTime": 40083,
      "Type": 1
    },
    {
      "EndTime": 40533,
      "Lane": 4,
      "StartTime": 40233,
      "Type": 2
    },
    {
      "EndTime": 40833,
      "Lane": 1,
      "StartTime": 40533,
      "Type": 2
    },
    {
      "EndTime": 40833,
      "Lane": 3,
      "StartTime": 40833,
      "Type": 1
    },
    {
      "EndTime": 41058,
      "Lane": 2,
      "StartTime": 41058,
      "Type": 1
    },
    {
      "EndTime": 41283,
      "Lane": 4,
      "StartTime": 41283,
      "Type": 1
    },
    {
      "EndTime": 41733,
      "Lane": 1,
      "StartTime": 41433,
      "Type": 2
    },
    {
      "EndTime": 41733,
      "Lane": 2,
      "StartTime": 41733,
      "Type": 1
    },
    {
      "EndTime": 41883,
      "Lane": 3,
      "StartTime": 41883,
      "Type": 1
    },
    {
      "EndTime": 42333,
      "Lane": 1,
      "StartTime": 42033,
      "Type": 2
    },
    {
      "EndTime": 42333,
      "Lane": 4,
      "StartTime": 42033,
      "Type": 2
    },
    {
      "EndTime": 42333,
      "Lane": 3,
      "StartTime": 42333,
      "Type": 1
    },
    {
      "EndTime": 42483,
      "Lane": 2,
      "StartTime": 42483,
      "Type": 1
    },
    {
      "EndTime": 42633,
      "Lane": 4,
      "StartTime": 42633,
      "Type": 1
    },
    {
      "EndTime": 42783,
      "Lane": 3,
      "StartTime": 42783,
      "Type": 1
    },
    {
      "EndTime": 43233,
      "Lane": 1,
      "StartTime": 42933,
      "Type": 2
    },
    {
      "EndTime": 43533,
      "Lane": 4,
      "StartTime": 43233,
      "Type": 2
    },
    {
      "EndTime": 43533,
      "Lane": 2,
      "StartTime": 43533,
      "Type": 1
    },
    {
      "EndTime": 43683,
      "Lane": 3,
      "StartTime": 43683,
      "Type": 1
    },
    {
      "EndTime": 44133,
      "Lane": 1,
      "StartTime": 43833,
      "Type": 2
    },
    {
      "EndTime": 43833,
      "Lane": 4,
      "StartTime": 43833,
      "Type": 1
    },
    {
      "EndTime": 44133,
      "Lane": 3,
      "StartTime": 44133,
      "Type": 1
    },
    {
      "EndTime": 44283,
      "Lane": 2,
      "StartTime": 44283,
      "Type": 1
    },
    {
      "EndTime": 44433,
      "Lane": 4,
      "StartTime": 44433,
      "Type": 1
    },
    {
      "EndTime": 44583,
      "Lane": 2,
      "StartTime": 44583,
      "Type": 1
    },
    {
      "EndTime": 45033,
      "Lane": 3,
      "StartTime": 44733,
      "Type": 2
    },
    {
      "EndTime": 45033,
      "Lane": 4,
      "StartTime": 44733,
      "Type": 2
    },
    {
      "EndTime": 45033,
      "Lane": 1,
      "StartTime": 45033,
      "Type": 1
    },
    {
      "EndTime": 45183,
      "Lane": 2,
      "StartTime": 45183,
      "Type": 1
    },
    {
      "EndTime": 45333,
      "Lane": 3,
      "StartTime": 45333,
      "Type": 1
    },
    {
      "EndTime": 45483,
      "Lane": 4,
      "StartTime": 45483,
      "Type": 1
    },
    {
      "EndTime": 45933,
      "Lane": 2,
      "StartTime": 45633,
      "Type": 2
    },
    {
      "EndTime": 45933,
      "Lane": 1,
      "StartTime": 45933,
      "Type": 1
    },
    {
      "EndTime": 46083,
      "Lane": 2,
      "StartTime": 46083,
      "Type": 1
    },
    {
      "EndTime": 46233,
      "Lane": 3,
      "StartTime": 46233,
      "Type": 1
    },
    {
      "EndTime": 46383,
      "Lane": 2,
      "StartTime": 46383,
      "Type": 1
    },
    {
      "EndTime": 46833,
      "Lane": 1,
      "StartTime": 46533,
      "Type": 2
    },
    {
      "EndTime": 46833,
      "Lane": 4,
      "StartTime": 46833,
      "Type": 1
    },
    {
      "EndTime": 47058,
      "Lane": 2,
      "StartTime": 47058,
      "Type": 1
    },
    {
      "EndTime": 47283,
      "Lane": 3,
      "StartTime": 47283,
      "Type": 1
    },
    {
      "EndTime": 47508,
      "Lane": 1,
      "StartTime": 47508,
      "Type": 1
    },
    {
      "EndTime": 48033,
      "Lane": 4,
      "StartTime": 47733,
      "Type": 2
    },
    {
      "EndTime": 48033,
      "Lane": 3,
      "StartTime": 48033,
      "Type": 1
    },
    {
      "EndTime": 48033,
      "Lane": 1,
      "StartTime": 48033,
      "Type": 1
    },
    {
      "EndTime": 48333,
      "Lane": 3,
      "StartTime": 48333,
      "Type": 1
    },
    {
      "EndTime": 48333,
      "Lane": 2,
      "StartTime": 48333,
      "Type": 1
    },
    {
      "EndTime": 48933,
      "Lane": 2,
      "StartTime": 48633,
      "Type": 2
    },
    {
      "EndTime": 48633,
      "Lane": 4,
      "StartTime": 48633,
      "Type": 1
    },
    {
      "EndTime": 49233,
      "Lane": 1,
      "StartTime": 48933,
      "Type": 2
    },
    {
      "EndTime": 50133,
      "Lane": 3,
      "StartTime": 49233,
      "Type": 2
    },
    {
      "EndTime": 50133,
      "Lane": 2,
      "StartTime": 49533,
      "Type": 2
    },
    {
      "EndTime": 50433,
      "Lane": 4,
      "StartTime": 50133,
      "Type": 2
    },
    {
      "EndTime": 50133,
      "Lane": 1,
      "StartTime": 50133,
      "Type": 1
    },
    {
      "EndTime": 50433,
      "Lane": 2,
      "StartTime": 50433,
      "Type": 1
    },
    {
      "EndTime": 50433,
      "Lane": 3,
      "StartTime": 50433,
      "Type": 1
    },
    {
      "EndTime": 50583,
      "Lane": 1,
      "StartTime": 50583,
      "Type": 1
    },
    {
      "EndTime": 50733,
      "Lane": 4,
      "StartTime": 50733,
      "Type": 1
    },
    {
      "EndTime": 50883,
      "Lane": 3,
      "StartTime": 50883,
      "Type": 1
    },
    {
      "EndTime": 51033,
      "Lane": 1,
      "StartTime": 51033,
      "Type": 1
    },
    {
      "EndTime": 51183,
      "Lane": 3,
      "StartTime": 51183,
      "Type": 1
    },
    {
      "EndTime": 51333,
      "Lane": 2,
      "StartTime": 51333,
      "Type": 1
    },
    {
      "EndTime": 51483,
      "Lane": 1,
      "StartTime": 51483,
      "Type": 1
    },
    {
      "EndTime": 51933,
      "Lane": 4,
      "StartTime": 51633,
      "Type": 2
    },
    {
      "EndTime": 51933,
      "Lane": 3,
      "StartTime": 51633,
      "Type": 2
    },
    {
      "EndTime": 51933,
      "Lane": 1,
      "StartTime": 51933,
      "Type": 1
    },
    {
      "EndTime": 52083,
      "Lane": 2,
      "StartTime": 52083,
      "Type": 1
    },
    {
      "EndTime": 52233,
      "Lane": 4,
      "StartTime": 52233,
      "Type": 1
    },
    {
      "EndTime": 52383,
      "Lane": 3,
      "StartTime": 52383,
      "Type": 1
    },
    {
      "EndTime": 52533,
      "Lane": 2,
      "StartTime": 52533,
      "Type": 1
    },
    {
      "EndTime": 52683,
      "Lane": 3,
      "StartTime": 52683,
      "Type": 1
    },
    {
      "EndTime": 52833,
      "Lane": 1,
      "StartTime": 52833,
      "Type": 1
    },
    {
      "EndTime": 52833,
      "Lane": 4,
      "StartTime": 52833,
      "Type": 1
    },
    {
      "EndTime": 52983,
      "Lane": 2,
      "StartTime": 52983,
      "Type": 1
    },
    {
      "EndTime": 53133,
      "Lane": 3,
      "StartTime": 53133,
      "Type": 1
    },
    {
      "EndTime": 53283,
      "Lane": 1,
      "StartTime": 53283,
      "Type": 1
    },
    {
      "EndTime": 53358,
      "Lane": 2,
      "StartTime": 53358,
      "Type": 1
    },
    {
      "EndTime": 53433,
      "Lane": 3,
      "StartTime": 53433,
      "Type": 1
    },
    {
      "EndTime": 53583,
      "Lane": 1,
      "StartTime": 53583,
      "Type": 1
    },
    {
      "EndTime": 53733,
      "Lane": 4,
      "StartTime": 53733,
      "Type": 1
    },
    {
      "EndTime": 53883,
      "Lane": 3,
      "StartTime": 53883,
      "Type": 1
    },
    {
      "EndTime": 53958,
      "Lane": 2,
      "StartTime": 53958,
      "Type": 1
    },
    {
      "EndTime": 54333,
      "Lane": 1,
      "StartTime": 54033,
      "Type": 2
    },
    {
      "EndTime": 54633,
      "Lane": 4,
      "StartTime": 54333,
      "Type": 2
    },
    {
      "EndTime": 54633,
      "Lane": 1,
      "StartTime": 54633,
      "Type": 1
    },
    {
      "EndTime": 54633,
      "Lane": 3,
      "StartTime": 54633,
      "Type": 1
    },
    {
      "EndTime": 54783,
      "Lane": 2,
      "StartTime": 54783,
      "Type": 1
    },
    {
      "EndTime": 55233,
      "Lane": 3,
      "StartTime": 54933,
      "Type": 2
    },
    {
      "EndTime": 55233,
      "Lane": 4,
      "StartTime": 54933,
      "Type": 2
    },
    {
      "EndTime": 55533,
      "Lane": 1,
      "StartTime": 55233,
      "Type": 2
    },
    {
      "EndTime": 55383,
      "Lane": 2,
      "StartTime": 55383,
      "Type": 1
    },
    {
      "EndTime": 55833,
      "Lane": 4,
      "StartTime": 55533,
      "Type": 2
    },
    {
      "EndTime": 55683,
      "Lane": 3,
      "StartTime": 55683,
      "Type": 1
    },
    {
      "EndTime": 55833,
      "Lane": 1,
      "StartTime": 55833,
      "Type": 1
    },
    {
      "EndTime": 55983,
      "Lane": 4,
      "StartTime": 55983,
      "Type": 1
    },
    {
      "EndTime": 56133,
      "Lane": 3,
      "StartTime": 56133,
      "Type": 1
    },
    {
      "EndTime": 56283,
      "Lane": 2,
      "StartTime": 56283,
      "Type": 1
    },
    {
      "EndTime": 56433,
      "Lane": 4,
      "StartTime": 56433,
      "Type": 1
    },
    {
      "EndTime": 56433,
      "Lane": 1,
      "StartTime": 56433,
      "Type": 1
    },
    {
      "EndTime": 56583,
      "Lane": 3,
      "StartTime": 56583,
      "Type": 1
    },
    {
      "EndTime": 56733,
      "Lane": 2,
      "StartTime": 56733,
      "Type": 1
    },
    {
      "EndTime": 56883,
      "Lane": 3,
      "StartTime": 56883,
      "Type": 1
    },
    {
      "EndTime": 56883,
      "Lane": 4,
      "StartTime": 56883,
      "Type": 1
    },
    {
      "EndTime": 57033,
      "Lane": 1,
      "StartTime": 57033,
      "Type": 1
    },
    {
      "EndTime": 57183,
      "Lane": 2,
      "StartTime": 57183,
      "Type": 1
    },
    {
      "EndTime": 57633,
      "Lane": 3,
      "StartTime": 57333,
      "Type": 2
    },
    {
      "EndTime": 57333,
      "Lane": 4,
      "StartTime": 57333,
      "Type": 1
    },
    {
      "EndTime": 57633,
      "Lane": 1,
      "StartTime": 57633,
      "Type": 1
    },
    {
      "EndTime": 57783,
      "Lane": 2,
      "StartTime": 57783,
      "Type": 1
    },
    {
      "EndTime": 57933,
      "Lane": 3,
      "StartTime": 57933,
      "Type": 1
    },
    {
      "EndTime": 58083,
      "Lane": 1,
      "StartTime": 58083,
      "Type": 1
    },
    {
      "EndTime": 58233,
      "Lane": 4,
      "StartTime": 58233,
      "Type": 1
    },
    {
      "EndTime": 58383,
      "Lane": 2,
      "StartTime": 58383,
      "Type": 1
    },
    {
      "EndTime": 58533,
      "Lane": 4,
      "StartTime": 58533,
      "Type": 1
    },
    {
      "EndTime": 58833,
      "Lane": 3,
      "StartTime": 58533,
      "Type": 2
    },
    {
      "EndTime": 61233,
      "Lane": 1,
      "StartTime": 58833,
      "Type": 2
    },
    {
      "EndTime": 58833,
      "Lane": 2,
      "StartTime": 58833,
      "Type": 1
    },
    {
      "EndTime": 60633,
      "Lane": 4,
      "StartTime": 60633,
      "Type": 1
    },
    {
      "EndTime": 63633,
      "Lane": 3,
      "StartTime": 61233,
      "Type": 2
    },
    {
      "EndTime": 62433,
      "Lane": 1,
      "StartTime": 62433,
      "Type": 1
    },
    {
      "EndTime": 63033,
      "Lane": 2,
      "StartTime": 63033,
      "Type": 1
    },
    {
      "EndTime": 64833,
      "Lane": 4,
      "StartTime": 63633,
      "Type": 2
    },
    {
      "EndTime": 66033,
      "Lane": 2,
      "StartTime": 64833,
      "Type": 2
    },
    {
      "EndTime": 65433,
      "Lane": 4,
      "StartTime": 65433,
      "Type": 1
    },
    {
      "EndTime": 65733,
      "Lane": 1,
      "StartTime": 65733,
      "Type": 1
    },
    {
      "EndTime": 68433,
      "Lane": 3,
      "StartTime": 66033,
      "Type": 2
    },
    {
      "EndTime": 66483,
      "Lane": 2,
      "StartTime": 66483,
      "Type": 1
    },
    {
      "EndTime": 66933,
      "Lane": 1,
      "StartTime": 66933,
      "Type": 1
    },
    {
      "EndTime": 67083,
      "Lane": 4,
      "StartTime": 67083,
      "Type": 1
    },
    {
      "EndTime": 68433,
      "Lane": 2,
      "StartTime": 67233,
      "Type": 2
    },
    {
      "EndTime": 70833,
      "Lane": 1,
      "StartTime": 68433,
      "Type": 2
    },
    {
      "EndTime": 68433,
      "Lane": 4,
      "StartTime": 68433,
      "Type": 1
    },
    {
      "EndTime": 68733,
      "Lane": 3,
      "StartTime": 68733,
      "Type": 1
    },
    {
      "EndTime": 69033,
      "Lane": 2,
      "StartTime": 69033,
      "Type": 1
    },
    {
      "EndTime": 69333,
      "Lane": 4,
      "StartTime": 69333,
      "Type": 1
    },
    {
      "EndTime": 69633,
      "Lane": 3,
      "StartTime": 69633,
      "Type": 1
    },
    {
      "EndTime": 69933,
      "Lane": 4,
      "StartTime": 69933,
      "Type": 1
    },
    {
      "EndTime": 70233,
      "Lane": 2,
      "StartTime": 70233,
      "Type": 1
    },
    {
      "EndTime": 70533,
      "Lane": 3,
      "StartTime": 70533,
      "Type": 1
    },
    {
      "EndTime": 73233,
      "Lane": 4,
      "StartTime": 70833,
      "Type": 2
    },
    {
      "EndTime": 71133,
      "Lane": 1,
      "StartTime": 71133,
      "Type": 1
    },
    {
      "EndTime": 71433,
      "Lane": 2,
      "StartTime": 71433,
      "Type": 1
    },
    {
      "EndTime": 71733,
      "Lane": 3,
      "StartTime": 71733,
      "Type": 1
    },
    {
      "EndTime": 72033,
      "Lane": 1,
      "StartTime": 72033,
      "Type": 1
    },
    {
      "EndTime": 72333,
      "Lane": 2,
      "StartTime": 72333,
      "Type": 1
    },
    {
      "EndTime": 72633,
      "Lane": 1,
      "StartTime": 72633,
      "Type": 1
    },
    {
      "EndTime": 73233,
      "Lane": 3,
      "StartTime": 72633,
      "Type": 2
    },
    {
      "EndTime": 73533,
      "Lane": 2,
      "StartTime": 73233,
      "Type": 2
    },
    {
      "EndTime": 73533,
      "Lane": 1,
      "StartTime": 73533,
      "Type": 1
    },
    {
      "EndTime": 73533,
      "Lane": 4,
      "StartTime": 73533,
      "Type": 1
    },
    {
      "EndTime": 73683,
      "Lane": 2,
      "StartTime": 73683,
      "Type": 1
    },
    {
      "EndTime": 73833,
      "Lane": 4,
      "StartTime": 73833,
      "Type": 1
    },
    {
      "EndTime": 73983,
      "Lane": 3,
      "StartTime": 73983,
      "Type": 1
    },
    {
      "EndTime": 74133,
      "Lane": 2,
      "StartTime": 74133,
      "Type": 1
    },
    {
      "EndTime": 74283,
      "Lane": 3,
      "StartTime": 74283,
      "Type": 1
    },
    {
      "EndTime": 74433,
      "Lane": 4,
      "StartTime": 74433,
      "Type": 1
    },
    {
      "EndTime": 74583,
      "Lane": 1,
      "StartTime": 74583,
      "Type": 1
    },
    {
      "EndTime": 74733,
      "Lane": 4,
      "StartTime": 74733,
      "Type": 1
    },
    {
      "EndTime": 74733,
      "Lane": 2,
      "StartTime": 74733,
      "Type": 1
    },
    {
      "EndTime": 74883,
      "Lane": 3,
      "StartTime": 74883,
      "Type": 1
    },
    {
      "EndTime": 75033,
      "Lane": 4,
      "StartTime": 75033,
      "Type": 1
    },
    {
      "EndTime": 75183,
      "Lane": 1,
      "StartTime": 75183,
      "Type": 1
    },
    {
      "EndTime": 75333,
      "Lane": 2,
      "StartTime": 75333,
      "Type": 1
    },
    {
      "EndTime": 75483,
      "Lane": 3,
      "StartTime": 75483,
      "Type": 1
    },
    {
      "EndTime": 75633,
      "Lane": 4,
      "StartTime": 75633,
      "Type": 1
    },
    {
      "EndTime": 75633,
      "Lane": 1,
      "StartTime": 75633,
      "Type": 1
    },
    {
      "EndTime": 75783,
      "Lane": 2,
      "StartTime": 75783,
      "Type": 1
    },
    {
      "EndTime": 75933,
      "Lane": 4,
      "StartTime": 75933,
      "Type": 1
    },
    {
      "EndTime": 76083,
      "Lane": 3,
      "StartTime": 76083,
      "Type": 1
    },
    {
      "EndTime": 76833,
      "Lane": 2,
      "StartTime": 76233,
      "Type": 2
    },
    {
      "EndTime": 76233,
      "Lane": 1,
      "StartTime": 76233,
      "Type": 1
    },
    {
      "EndTime": 76833,
      "Lane": 3,
      "StartTime": 76533,
      "Type": 2
    },
    {
      "EndTime": 77433,
      "Lane": 4,
      "StartTime": 76833,
      "Type": 2
    },
    {
      "EndTime": 77583,
      "Lane": 1,
      "StartTime": 77583,
      "Type": 1
    },
    {
      "EndTime": 77733,
      "Lane": 3,
      "StartTime": 77733,
      "Type": 1
    },
    {
      "EndTime": 77883,
      "Lane": 2,
      "StartTime": 77883,
      "Type": 1
    },
    {
      "EndTime": 78033,
      "Lane": 1,
      "StartTime": 78033,
      "Type": 1
    },
    {
      "EndTime": 78033,
      "Lane": 4,
      "StartTime": 78033,
      "Type": 1
    },
    {
      "EndTime": 78183,
      "Lane": 3,
      "StartTime": 78183,
      "Type": 1
    },
    {
      "EndTime": 78333,
      "Lane": 2,
      "StartTime": 78333,
      "Type": 1
    },
    {
      "EndTime": 78483,
      "Lane": 1,
      "StartTime": 78483,
      "Type": 1
    },
    {
      "EndTime": 78633,
      "Lane": 4,
      "StartTime": 78633,
      "Type": 1
    },
    {
      "EndTime": 78783,
      "Lane": 2,
      "StartTime": 78783,
      "Type": 1
    },
    {
      "EndTime": 78933,
      "Lane": 3,
      "StartTime": 78933,
      "Type": 1
    },
    {
      "EndTime": 79383,
      "Lane": 4,
      "StartTime": 79083,
      "Type": 2
    },
    {
      "EndTime": 79383,
      "Lane": 1,
      "StartTime": 79383,
      "Type": 1
    },
    {
      "EndTime": 79533,
      "Lane": 2,
      "StartTime": 79533,
      "Type": 1
    },
    {
      "EndTime": 79683,
      "Lane": 3,
      "StartTime": 79683,
      "Type": 1
    },
    {
      "EndTime": 79833,
      "Lane": 1,
      "StartTime": 79833,
      "Type": 1
    },
    {
      "EndTime": 79983,
      "Lane": 4,
      "StartTime": 79983,
      "Type": 1
    },
    {
      "EndTime": 80133,
      "Lane": 3,
      "StartTime": 80133,
      "Type": 1
    },
    {
      "EndTime": 80283,
      "Lane": 2,
      "StartTime": 80283,
      "Type": 1
    },
    {
      "EndTime": 80433,
      "Lane": 1,
      "StartTime": 80433,
      "Type": 1
    },
    {
      "EndTime": 80583,
      "Lane": 4,
      "StartTime": 80583,
      "Type": 1
    },
    {
      "EndTime": 80733,
      "Lane": 2,
      "StartTime": 80733,
      "Type": 1
    },
    {
      "EndTime": 80883,
      "Lane": 3,
      "StartTime": 80883,
      "Type": 1
    },
    {
      "EndTime": 81033,
      "Lane": 1,
      "StartTime": 81033,
      "Type": 1
    },
    {
      "EndTime": 81183,
      "Lane": 2,
      "StartTime": 81183,
      "Type": 1
    },
    {
      "EndTime": 81333,
      "Lane": 3,
      "StartTime": 81333,
      "Type": 1
    },
    {
      "EndTime": 81483,
      "Lane": 4,
      "StartTime": 81483,
      "Type": 1
    },
    {
      "EndTime": 81933,
      "Lane": 2,
      "StartTime": 81633,
      "Type": 2
    },
    {
      "EndTime": 81633,
      "Lane": 1,
      "StartTime": 81633,
      "Type": 1
    },
    {
      "EndTime": 82233,
      "Lane": 3,
      "StartTime": 81933,
      "Type": 2
    },
    {
      "EndTime": 81933,
      "Lane": 4,
      "StartTime": 81933,
      "Type": 1
    },
    {
      "EndTime": 82233,
      "Lane": 1,
      "StartTime": 82233,
      "Type": 1
    },
    {
      "EndTime": 82533,
      "Lane": 4,
      "StartTime": 82233,
      "Type": 2
    },
    {
      "EndTime": 82833,
      "Lane": 1,
      "StartTime": 82533,
      "Type": 2
    },
    {
      "EndTime": 82533,
      "Lane": 3,
      "StartTime": 82533,
      "Type": 1
    },
    {
      "EndTime": 82833,
      "Lane": 2,
      "StartTime": 82833,
      "Type": 1
    },
    {
      "EndTime": 82833,
      "Lane": 4,
      "StartTime": 82833,
      "Type": 1
    },
    {
      "EndTime": 82983,
      "Lane": 3,
      "StartTime": 82983,
      "Type": 1
    },
    {
      "EndTime": 83133,
      "Lane": 1,
      "StartTime": 83133,
      "Type": 1
    },
    {
      "EndTime": 83283,
      "Lane": 2,
      "StartTime": 83283,
      "Type": 1
    },
    {
      "EndTime": 83583,
      "Lane": 3,
      "StartTime": 83583,
      "Type": 1
    },
    {
      "EndTime": 83733,
      "Lane": 1,
      "StartTime": 83733,
      "Type": 1
    },
    {
      "EndTime": 84183,
      "Lane": 2,
      "StartTime": 83883,
      "Type": 2
    },
    {
      "EndTime": 84183,
      "Lane": 4,
      "StartTime": 84183,
      "Type": 1
    },
    {
      "EndTime": 84333,
      "Lane": 3,
      "StartTime": 84333,
      "Type": 1
    },
    {
      "EndTime": 84483,
      "Lane": 2,
      "StartTime": 84483,
      "Type": 1
    },
    {
      "EndTime": 84633,
      "Lane": 4,
      "StartTime": 84633,
      "Type": 1
    },
    {
      "EndTime": 84783,
      "Lane": 1,
      "StartTime": 84783,
      "Type": 1
    },
    {
      "EndTime": 84933,
      "Lane": 3,
      "StartTime": 84933,
      "Type": 1
    },
    {
      "EndTime": 85083,
      "Lane": 4,
      "StartTime": 85083,
      "Type": 1
    },
    {
      "EndTime": 85233,
      "Lane": 2,
      "StartTime": 85233,
      "Type": 1
    },
    {
      "EndTime": 85383,
      "Lane": 3,
      "StartTime": 85383,
      "Type": 1
    },
    {
      "EndTime": 85533,
      "Lane": 4,
      "StartTime": 85533,
      "Type": 1
    },
    {
      "EndTime": 85533,
      "Lane": 2,
      "StartTime": 85533,
      "Type": 1
    },
    {
      "EndTime": 85683,
      "Lane": 1,
      "StartTime": 85683,
      "Type": 1
    },
    {
      "EndTime": 85833,
      "Lane": 3,
      "StartTime": 85833,
      "Type": 1
    },
    {
      "EndTime": 86133,
      "Lane": 4,
      "StartTime": 85983,
      "Type": 2
    },
    {
      "EndTime": 86283,
      "Lane": 2,
      "StartTime": 86133,
      "Type": 2
    },
    {
      "EndTime": 86433,
      "Lane": 1,
      "StartTime": 86283,
      "Type": 2
    },
    {
      "EndTime": 86433,
      "Lane": 4,
      "StartTime": 86433,
      "Type": 1
    },
    {
      "EndTime": 86583,
      "Lane": 2,
      "StartTime": 86583,
      "Type": 1
    },
    {
      "EndTime": 86733,
      "Lane": 3,
      "StartTime": 86733,
      "Type": 1
    },
    {
      "EndTime": 86883,
      "Lane": 4,
      "StartTime": 86883,
      "Type": 1
    },
    {
      "EndTime": 87633,
      "Lane": 1,
      "StartTime": 87033,
      "Type": 2
    },
    {
      "EndTime": 87633,
      "Lane": 2,
      "StartTime": 87333,
      "Type": 2
    },
    {
      "EndTime": 87633,
      "Lane": 3,
      "StartTime": 87633,
      "Type": 1
    },
    {
      "EndTime": 87633,
      "Lane": 4,
      "StartTime": 87633,
      "Type": 1
    },
    {
      "EndTime": 87933,
      "Lane": 4,
      "StartTime": 87933,
      "Type": 1
    },
    {
      "EndTime": 87933,
      "Lane": 1,
      "StartTime": 87933,
      "Type": 1
    },
    {
      "EndTime": 88233,
      "Lane": 2,
      "StartTime": 88233,
      "Type": 1
    },
    {
      "EndTime": 88233,
      "Lane": 1,
      "StartTime": 88233,
      "Type": 1
    },
    {
      "EndTime": 88533,
      "Lane": 2,
      "StartTime": 88533,
      "Type": 1
    },
    {
      "EndTime": 88533,
      "Lane": 4,
      "StartTime": 88533,
      "Type": 1
    },
    {
      "EndTime": 88833,
      "Lane": 1,
      "StartTime": 88833,
      "Type": 1
    },
    {
      "EndTime": 88833,
      "Lane": 3,
      "StartTime": 88833,
      "Type": 1
    },
    {
      "EndTime": 89133,
      "Lane": 3,
      "StartTime": 89133,
      "Type": 1
    },
    {
      "EndTime": 89133,
      "Lane": 4,
      "StartTime": 89133,
      "Type": 1
    },
    {
      "EndTime": 89433,
      "Lane": 4,
      "StartTime": 89433,
      "Type": 1
    },
    {
      "EndTime": 89433,
      "Lane": 1,
      "StartTime": 89433,
      "Type": 1
    },
    {
      "EndTime": 89733,
      "Lane": 3,
      "StartTime": 89733,
      "Type": 1
    },
    {
      "EndTime": 89733,
      "Lane": 2,
      "StartTime": 89733,
      "Type": 1
    },
    {
      "EndTime": 90033,
      "Lane": 1,
      "StartTime": 90033,
      "Type": 1
    },
    {
      "EndTime": 90033,
      "Lane": 2,
      "StartTime": 90033,
      "Type": 1
    },
    {
      "EndTime": 90333,
      "Lane": 3,
      "StartTime": 90333,
      "Type": 1
    },
    {
      "EndTime": 90333,
      "Lane": 1,
      "StartTime": 90333,
      "Type": 1
    },
    {
      "EndTime": 90633,
      "Lane": 3,
      "StartTime": 90633,
      "Type": 1
    },
    {
      "EndTime": 90633,
      "Lane": 4,
      "StartTime": 90633,
      "Type": 1
    },
    {
      "EndTime": 90933,
      "Lane": 2,
      "StartTime": 90933,
      "Type": 1
    },
    {
      "EndTime": 90933,
      "Lane": 4,
      "StartTime": 90933,
      "Type": 1
    },
    {
      "EndTime": 91533,
      "Lane": 1,
      "StartTime": 91233,
      "Type": 2
    },
    {
      "EndTime": 91233,
      "Lane": 3,
      "StartTime": 91233,
      "Type": 1
    },
    {
      "EndTime": 91833,
      "Lane": 2,
      "StartTime": 91533,
      "Type": 2
    },
    {
      "EndTime": 91533,
      "Lane": 4,
      "StartTime": 91533,
      "Type": 1
    },
    {
      "EndTime": 91833,
      "Lane": 1,
      "StartTime": 91833,
      "Type": 1
    },
    {
      "EndTime": 92133,
      "Lane": 3,
      "StartTime": 91833,
      "Type": 2
    },
    {
      "EndTime": 92433,
      "Lane": 2,
      "StartTime": 92133,
      "Type": 2
    },
    {
      "EndTime": 92133,
      "Lane": 4,
      "StartTime": 92133,
      "Type": 1
    },
    {
      "EndTime": 92433,
      "Lane": 1,
      "StartTime": 92433,
      "Type": 1
    },
    {
      "EndTime": 92433,
      "Lane": 4,
      "StartTime": 92433,
      "Type": 1
    },
    {
      "EndTime": 94533,
      "Lane": 2,
      "StartTime": 94533,
      "Type": 1
    },
    {
      "EndTime": 94833,
      "Lane": 3,
      "StartTime": 94533,
      "Type": 2
    },
    {
      "EndTime": 94833,
      "Lane": 1,
      "StartTime": 94833,
      "Type": 1
    },
    {
      "EndTime": 94983,
      "Lane": 3,
      "StartTime": 94983,
      "Type": 1
    },
    {
      "EndTime": 95133,
      "Lane": 2,
      "StartTime": 95133,
      "Type": 1
    },
    {
      "EndTime": 95283,
      "Lane": 4,
      "StartTime": 95283,
      "Type": 1
    },
    {
      "EndTime": 95433,
      "Lane": 1,
      "StartTime": 95433,
      "Type": 1
    },
    {
      "EndTime": 95583,
      "Lane": 3,
      "StartTime": 95583,
      "Type": 1
    },
    {
      "EndTime": 95733,
      "Lane": 2,
      "StartTime": 95733,
      "Type": 1
    },
    {
      "EndTime": 95883,
      "Lane": 1,
      "StartTime": 95883,
      "Type": 1
    },
    {
      "EndTime": 96633,
      "Lane": 4,
      "StartTime": 96033,
      "Type": 2
    },
    {
      "EndTime": 96183,
      "Lane": 2,
      "StartTime": 96183,
      "Type": 1
    },
    {
      "EndTime": 96333,
      "Lane": 1,
      "StartTime": 96333,
      "Type": 1
    },
    {
      "EndTime": 96483,
      "Lane": 3,
      "StartTime": 96483,
      "Type": 1
    },
    {
      "EndTime": 96633,
      "Lane": 2,
      "StartTime": 96633,
      "Type": 1
    },
    {
      "EndTime": 96933,
      "Lane": 3,
      "StartTime": 96933,
      "Type": 1
    },
    {
      "EndTime": 97233,
      "Lane": 4,
      "StartTime": 97233,
      "Type": 1
    },
    {
      "EndTime": 97233,
      "Lane": 1,
      "StartTime": 97233,
      "Type": 1
    },
    {
      "EndTime": 97383,
      "Lane": 2,
      "StartTime": 97383,
      "Type": 1
    },
    {
      "EndTime": 97533,
      "Lane": 3,
      "StartTime": 97533,
      "Type": 1
    },
    {
      "EndTime": 97683,
      "Lane": 1,
      "StartTime": 97683,
      "Type": 1
    },
    {
      "EndTime": 97833,
      "Lane": 4,
      "StartTime": 97833,
      "Type": 1
    },
    {
      "EndTime": 97983,
      "Lane": 2,
      "StartTime": 97983,
      "Type": 1
    },
    {
      "EndTime": 98133,
      "Lane": 3,
      "StartTime": 98133,
      "Type": 1
    },
    {
      "EndTime": 98283,
      "Lane": 1,
      "StartTime": 98283,
      "Type": 1
    },
    {
      "EndTime": 98433,
      "Lane": 2,
      "StartTime": 98433,
      "Type": 1
    },
    {
      "EndTime": 98583,
      "Lane": 4,
      "StartTime": 98583,
      "Type": 1
    },
    {
      "EndTime": 98733,
      "Lane": 1,
      "StartTime": 98733,
      "Type": 1
    },
    {
      "EndTime": 98883,
      "Lane": 3,
      "StartTime": 98883,
      "Type": 1
    },
    {
      "EndTime": 99033,
      "Lane": 2,
      "StartTime": 99033,
      "Type": 1
    },
    {
      "EndTime": 99183,
      "Lane": 1,
      "StartTime": 99183,
      "Type": 1
    },
    {
      "EndTime": 99333,
      "Lane": 4,
      "StartTime": 99333,
      "Type": 1
    },
    {
      "EndTime": 99483,
      "Lane": 2,
      "StartTime": 99483,
      "Type": 1
    },
    {
      "EndTime": 99933,
      "Lane": 3,
      "StartTime": 99633,
      "Type": 2
    },
    {
      "EndTime": 99933,
      "Lane": 1,
      "StartTime": 99933,
      "Type": 1
    },
    {
      "EndTime": 100383,
      "Lane": 2,
      "StartTime": 100083,
      "Type": 2
    },
    {
      "EndTime": 100383,
      "Lane": 4,
      "StartTime": 100383,
      "Type": 1
    },
    {
      "EndTime": 100533,
      "Lane": 1,
      "StartTime": 100533,
      "Type": 1
    },
    {
      "EndTime": 100683,
      "Lane": 3,
      "StartTime": 100683,
      "Type": 1
    },
    {
      "EndTime": 101133,
      "Lane": 4,
      "StartTime": 100833,
      "Type": 2
    },
    {
      "EndTime": 100983,
      "Lane": 1,
      "StartTime": 100983,
      "Type": 1
    },
    {
      "EndTime": 101133,
      "Lane": 2,
      "StartTime": 101133,
      "Type": 1
    },
    {
      "EndTime": 101283,
      "Lane": 3,
      "StartTime": 101283,
      "Type": 1
    },
    {
      "EndTime": 102033,
      "Lane": 1,
      "StartTime": 101433,
      "Type": 2
    },
    {
      "EndTime": 101583,
      "Lane": 4,
      "StartTime": 101583,
      "Type": 1
    },
    {
      "EndTime": 101733,
      "Lane": 3,
      "StartTime": 101733,
      "Type": 1
    },
    {
      "EndTime": 101883,
      "Lane": 2,
      "StartTime": 101883,
      "Type": 1
    },
    {
      "EndTime": 102033,
      "Lane": 4,
      "StartTime": 102033,
      "Type": 1
    },
    {
      "EndTime": 102183,
      "Lane": 1,
      "StartTime": 102183,
      "Type": 1
    },
    {
      "EndTime": 102333,
      "Lane": 3,
      "StartTime": 102333,
      "Type": 1
    },
    {
      "EndTime": 102783,
      "Lane": 2,
      "StartTime": 102483,
      "Type": 2
    },
    {
      "EndTime": 102783,
      "Lane": 4,
      "StartTime": 102783,
      "Type": 1
    },
    {
      "EndTime": 102933,
      "Lane": 2,
      "StartTime": 102933,
      "Type": 1
    },
    {
      "EndTime": 103083,
      "Lane": 3,
      "StartTime": 103083,
      "Type": 1
    },
    {
      "EndTime": 103533,
      "Lane": 1,
      "StartTime": 103233,
      "Type": 2
    },
    {
      "EndTime": 103383,
      "Lane": 4,
      "StartTime": 103383,
      "Type": 1
    },
    {
      "EndTime": 103833,
      "Lane": 3,
      "StartTime": 103533,
      "Type": 2
    },
    {
      "EndTime": 104133,
      "Lane": 2,
      "StartTime": 103833,
      "Type": 2
    },
    {
      "EndTime": 103983,
      "Lane": 3,
      "StartTime": 103983,
      "Type": 1
    },
    {
      "EndTime": 104433,
      "Lane": 4,
      "StartTime": 104133,
      "Type": 2
    },
    {
      "EndTime": 104283,
      "Lane": 1,
      "StartTime": 104283,
      "Type": 1
    },
    {
      "EndTime": 104433,
      "Lane": 3,
      "StartTime": 104433,
      "Type": 1
    },
    {
      "EndTime": 104433,
      "Lane": 2,
      "StartTime": 104433,
      "Type": 1
    },
    {
      "EndTime": 104583,
      "Lane": 1,
      "StartTime": 104583,
      "Type": 1
    },
    {
      "EndTime": 104733,
      "Lane": 3,
      "StartTime": 104733,
      "Type": 1
    },
    {
      "EndTime": 104883,
      "Lane": 2,
      "StartTime": 104883,
      "Type": 1
    },
    {
      "EndTime": 105033,
      "Lane": 4,
      "StartTime": 105033,
      "Type": 1
    },
    {
      "EndTime": 105183,
      "Lane": 1,
      "StartTime": 105183,
      "Type": 1
    },
    {
      "EndTime": 105633,
      "Lane": 3,
      "StartTime": 105333,
      "Type": 2
    },
    {
      "EndTime": 105483,
      "Lane": 2,
      "StartTime": 105483,
      "Type": 1
    },
    {
      "EndTime": 105633,
      "Lane": 4,
      "StartTime": 105633,
      "Type": 1
    },
    {
      "EndTime": 106233,
      "Lane": 1,
      "StartTime": 105633,
      "Type": 2
    },
    {
      "EndTime": 105783,
      "Lane": 3,
      "StartTime": 105783,
      "Type": 1
    },
    {
      "EndTime": 105933,
      "Lane": 2,
      "StartTime": 105933,
      "Type": 1
    },
    {
      "EndTime": 106083,
      "Lane": 4,
      "StartTime": 106083,
      "Type": 1
    },
    {
      "EndTime": 106833,
      "Lane": 3,
      "StartTime": 106233,
      "Type": 2
    },
    {
      "EndTime": 106383,
      "Lane": 1,
      "StartTime": 106383,
      "Type": 1
    },
    {
      "EndTime": 106533,
      "Lane": 4,
      "StartTime": 106533,
      "Type": 1
    },
    {
      "EndTime": 106683,
      "Lane": 2,
      "StartTime": 106683,
      "Type": 1
    },
    {
      "EndTime": 106833,
      "Lane": 1,
      "StartTime": 106833,
      "Type": 1
    },
    {
      "EndTime": 106833,
      "Lane": 4,
      "StartTime": 106833,
      "Type": 1
    },
    {
      "EndTime": 106983,
      "Lane": 3,
      "StartTime": 106983,
      "Type": 1
    },
    {
      "EndTime": 107133,
      "Lane": 2,
      "StartTime": 107133,
      "Type": 1
    },
    {
      "EndTime": 107283,
      "Lane": 4,
      "StartTime": 107283,
      "Type": 1
    },
    {
      "EndTime": 107433,
      "Lane": 1,
      "StartTime": 107433,
      "Type": 1
    },
    {
      "EndTime": 107583,
      "Lane": 2,
      "StartTime": 107583,
      "Type": 1
    },
    {
      "EndTime": 108033,
      "Lane": 3,
      "StartTime": 107733,
      "Type": 2
    },
    {
      "EndTime": 108333,
      "Lane": 4,
      "StartTime": 108033,
      "Type": 2
    },
    {
      "EndTime": 108183,
      "Lane": 1,
      "StartTime": 108183,
      "Type": 1
    },
    {
      "EndTime": 108333,
      "Lane": 2,
      "StartTime": 108333,
      "Type": 1
    },
    {
      "EndTime": 108483,
      "Lane": 4,
      "StartTime": 108483,
      "Type": 1
    },
    {
      "EndTime": 109233,
      "Lane": 1,
      "StartTime": 108633,
      "Type": 2
    },
    {
      "EndTime": 108783,
      "Lane": 3,
      "StartTime": 108783,
      "Type": 1
    },
    {
      "EndTime": 108933,
      "Lane": 2,
      "StartTime": 108933,
      "Type": 1
    },
    {
      "EndTime": 109083,
      "Lane": 4,
      "StartTime": 109083,
      "Type": 1
    },
    {
      "EndTime": 109233,
      "Lane": 3,
      "StartTime": 109233,
      "Type": 1
    },
    {
      "EndTime": 109383,
      "Lane": 2,
      "StartTime": 109383,
      "Type": 1
    },
    {
      "EndTime": 109533,
      "Lane": 1,
      "StartTime": 109533,
      "Type": 1
    },
    {
      "EndTime": 109683,
      "Lane": 3,
      "StartTime": 109683,
      "Type": 1
    },
    {
      "EndTime": 109833,
      "Lane": 2,
      "StartTime": 109833,
      "Type": 1
    },
    {
      "EndTime": 109983,
      "Lane": 4,
      "StartTime": 109983,
      "Type": 1
    },
    {
      "EndTime": 110133,
      "Lane": 1,
      "StartTime": 110133,
      "Type": 1
    },
    {
      "EndTime": 110283,
      "Lane": 2,
      "StartTime": 110283,
      "Type": 1
    },
    {
      "EndTime": 110733,
      "Lane": 3,
      "StartTime": 110433,
      "Type": 2
    },
    {
      "EndTime": 110583,
      "Lane": 1,
      "StartTime": 110583,
      "Type": 1
    },
    {
      "EndTime": 111033,
      "Lane": 2,
      "StartTime": 110733,
      "Type": 2
    },
    {
      "EndTime": 110883,
      "Lane": 4,
      "StartTime": 110883,
      "Type": 1
    },
    {
      "EndTime": 111333,
      "Lane": 3,
      "StartTime": 111033,
      "Type": 2
    },
    {
      "EndTime": 111183,
      "Lane": 1,
      "StartTime": 111183,
      "Type": 1
    },
    {
      "EndTime": 111633,
      "Lane": 4,
      "StartTime": 111333,
      "Type": 2
    },
    {
      "EndTime": 111483,
      "Lane": 2,
      "StartTime": 111483,
      "Type": 1
    },
    {
      "EndTime": 111633,
      "Lane": 1,
      "StartTime": 111633,
      "Type": 1
    },
    {
      "EndTime": 111783,
      "Lane": 3,
      "StartTime": 111783,
      "Type": 1
    },
    {
      "EndTime": 111933,
      "Lane": 4,
      "StartTime": 111933,
      "Type": 1
    },
    {
      "EndTime": 112083,
      "Lane": 1,
      "StartTime": 112083,
      "Type": 1
    },
    {
      "EndTime": 112233,
      "Lane": 3,
      "StartTime": 112233,
      "Type": 1
    },
    {
      "EndTime": 112383,
      "Lane": 2,
      "StartTime": 112383,
      "Type": 1
    },
    {
      "EndTime": 112533,
      "Lane": 4,
      "StartTime": 112533,
      "Type": 1
    },
    {
      "EndTime": 112683,
      "Lane": 3,
      "StartTime": 112683,
      "Type": 1
    },
    {
      "EndTime": 112833,
      "Lane": 1,
      "StartTime": 112833,
      "Type": 1
    },
    {
      "EndTime": 112983,
      "Lane": 2,
      "StartTime": 112983,
      "Type": 1
    },
    {
      "EndTime": 113133,
      "Lane": 3,
      "StartTime": 113133,
      "Type": 1
    },
    {
      "EndTime": 113283,
      "Lane": 1,
      "StartTime": 113283,
      "Type": 1
    },
    {
      "EndTime": 114033,
      "Lane": 2,
      "StartTime": 113433,
      "Type": 2
    },
    {
      "EndTime": 113433,
      "Lane": 3,
      "StartTime": 113433,
      "Type": 1
    },
    {
      "EndTime": 113583,
      "Lane": 4,
      "StartTime": 113583,
      "Type": 1
    },
    {
      "EndTime": 113733,
      "Lane": 1,
      "StartTime": 113733,
      "Type": 1
    },
    {
      "EndTime": 113883,
      "Lane": 3,
      "StartTime": 113883,
      "Type": 1
    },
    {
      "EndTime": 114033,
      "Lane": 4,
      "StartTime": 114033,
      "Type": 1
    },
    {
      "EndTime": 114033,
      "Lane": 1,
      "StartTime": 114033,
      "Type": 1
    },
    {
      "EndTime": 114183,
      "Lane": 2,
      "StartTime": 114183,
      "Type": 1
    },
    {
      "EndTime": 114333,
      "Lane": 4,
      "StartTime": 114333,
      "Type": 1
    },
    {
      "EndTime": 114483,
      "Lane": 1,
      "StartTime": 114483,
      "Type": 1
    },
    {
      "EndTime": 114633,
      "Lane": 3,
      "StartTime": 114633,
      "Type": 1
    },
    {
      "EndTime": 114783,
      "Lane": 4,
      "StartTime": 114783,
      "Type": 1
    },
    {
      "EndTime": 114933,
      "Lane": 1,
      "StartTime": 114933,
      "Type": 1
    },
    {
      "EndTime": 115083,
      "Lane": 2,
      "StartTime": 115083,
      "Type": 1
    },
    {
      "EndTime": 115233,
      "Lane": 3,
      "StartTime": 115233,
      "Type": 1
    },
    {
      "EndTime": 115383,
      "Lane": 4,
      "StartTime": 115383,
      "Type": 1
    },
    {
      "EndTime": 115533,
      "Lane": 2,
      "StartTime": 115533,
      "Type": 1
    },
    {
      "EndTime": 115683,
      "Lane": 4,
      "StartTime": 115683,
      "Type": 1
    },
    {
      "EndTime": 116433,
      "Lane": 1,
      "StartTime": 115833,
      "Type": 2
    },
    {
      "EndTime": 115833,
      "Lane": 3,
      "StartTime": 115833,
      "Type": 1
    },
    {
      "EndTime": 115983,
      "Lane": 2,
      "StartTime": 115983,
      "Type": 1
    },
    {
      "EndTime": 116133,
      "Lane": 4,
      "StartTime": 116133,
      "Type": 1
    },
    {
      "EndTime": 116283,
      "Lane": 3,
      "StartTime": 116283,
      "Type": 1
    },
    {
      "EndTime": 116433,
      "Lane": 2,
      "StartTime": 116433,
      "Type": 1
    },
    {
      "EndTime": 116433,
      "Lane": 4,
      "StartTime": 116433,
      "Type": 1
    },
    {
      "EndTime": 116583,
      "Lane": 1,
      "StartTime": 116583,
      "Type": 1
    },
    {
      "EndTime": 116733,
      "Lane": 4,
      "StartTime": 116733,
      "Type": 1
    },
    {
      "EndTime": 116733,
      "Lane": 3,
      "StartTime": 116733,
      "Type": 1
    },
    {
      "EndTime": 116883,
      "Lane": 2,
      "StartTime": 116883,
      "Type": 1
    },
    {
      "EndTime": 117033,
      "Lane": 1,
      "StartTime": 117033,
      "Type": 1
    },
    {
      "EndTime": 117033,
      "Lane": 4,
      "StartTime": 117033,
      "Type": 1
    },
    {
      "EndTime": 117183,
      "Lane": 3,
      "StartTime": 117183,
      "Type": 1
    },
    {
      "EndTime": 117333,
      "Lane": 1,
      "StartTime": 117333,
      "Type": 1
    },
    {
      "EndTime": 117333,
      "Lane": 2,
      "StartTime": 117333,
      "Type": 1
    },
    {
      "EndTime": 117483,
      "Lane": 3,
      "StartTime": 117483,
      "Type": 1
    },
    {
      "EndTime": 117483,
      "Lane": 4,
      "StartTime": 117483,
      "Type": 1
    }
  ],
  "InitialSliderVelocity": 1,
  "KeyCount": 4,
  "Metadata": {
    "Artist": "Aoi vs. r0y",
    "DifficultyName": "NOVICE",
    "Mapper": "Murumoo",
    "Title": "Coldlapse"
  },
  "Name": "Aoi vs. r0y - Coldlapse",
  "NoteOffset": 0,
  "Offset": -75,
  "PreviewTime": 0,
  "PrimaryBPM": 200,
  "Rating": {
    "0.75": 175,
    "1.00": 214,
    "1.50": 282
  },
  "SongRate": 1,
  "TimingPoints": {
    "BPM": [
      {
        "Inherrited": 0,
        "Signature": 0,
        "StartTime": 0,
        "Value": 240
      }
    ],
    "SV": {}
  },
  "Version": 3
}